[{"id":9405,"league":{"id":32,"name":"Copa Libertadores","country":"South America","is_women":false,"current_season":{"id":96,"name":"CONMEBOL Libertadores 2026","year":2026,"start_date":"2026-01-01","end_date":"2026-12-31"}},"home_team":"Universitario de Deportes","away_team":"Nacional","home_team_obj":{"id":782,"name":"Universitario de Deportes","short_name":"Universitario","country":"Peru","coach":{"name":"Jorge Araujo","shortName":"J. Araujo"},"venue":{"id":581,"name":"Estadio Monumental","city":"Lima","country":"Peru","capacity":80093}},"away_team_obj":{"id":784,"name":"Nacional","short_name":"Nacional","country":"Uruguay","coach":{"name":"Jorge Bava","shortName":"J. Bava"},"venue":{"id":583,"name":"Gran Parque Central","city":"Montevideo","country":"Uruguay","capacity":37000}},"event_date":"2026-04-30T06:00:00+04:00","group_name":null,"status":"1st_half","home_score":1,"away_score":1,"home_score_ht":null,"away_score_ht":null,"penalty_shootout":null,"current_minute":50,"period":"1T","home_xg_live":0.67,"away_xg_live":1.07,"incidents":[{"text":"First half","type":"period","minute":45,"is_live":true,"added_time":999,"away_score":1,"home_score":1},{"type":"injuryTime","length":6,"minute":45},{"type":"card","minute":43,"player":"M. Gómez","is_home":false,"card_type":"yellow","player_id":805245},{"type":"goal","assist":"J. Concha","minute":40,"player":"C. Fara","is_home":true,"sequence":[{"end":{"x":95.3,"y":42.6},"pid":924783,"pos":{"x":99.5,"y":99.5},"event":"cross","assist":true,"player":"J. Concha"},{"gk":{"x":99,"y":48.6},"gm":{"x":66.67,"y":44.17},"pid":971200,"pos":{"x":94.9,"y":45.3},"body":"left-foot","event":"goal","player":"C. Fara"}],"goal_type":"regular","player_id":971200,"away_score":1,"home_score":1},{"type":"card","minute":35,"player":"L. Rodríguez","is_home":false,"card_type":"yellowRed","player_id":586672},{"type":"card","minute":21,"player":"L. Rodríguez","is_home":false,"card_type":"yellow","player_id":586672},{"type":"card","minute":18,"player":"C. Fara","is_home":true,"card_type":"yellow","player_id":971200},{"type":"goal","minute":14,"player":"M. Gómez","is_home":false,"sequence":[{"gk":{"x":0.2,"y":49.6},"gm":{"x":50,"y":97.83},"pid":805245,"pos":{"x":11.6,"y":50},"body":"right-foot","event":"goal","player":"M. Gómez"}],"goal_type":"penalty","player_id":805245,"away_score":1,"home_score":0},{"type":"varDecision","minute":11,"player":"C. Cándido","is_home":false,"decision":"penaltyNotAwarded","confirmed":false,"player_id":924073}],"live_stats":{"away":{"duels":51,"fouls":7,"passes":120,"crosses":"2/6 (33%)","tackles":7,"dribbles":"2/6 (33%)","offsides":0,"red_cards":1,"throw_ins":10,"clearances":14,"free_kicks":5,"goal_kicks":2,"long_balls":"13/27 (48%)","recoveries":20,"big_chances":2,"tackles_won":57,"total_saves":1,"total_shots":5,"aerial_duels":"9/14 (64%)","corner_kicks":2,"dispossessed":6,"ground_duels":"14/31 (45%)","hit_woodwork":0,"yellow_cards":3,"blocked_shots":1,"interceptions":7,"total_tackles":7,"expected_goals":1.07,"accurate_passes":87,"ball_possession":40,"goals_prevented":0.24,"shots_on_target":3,"goalkeeper_saves":1,"shots_inside_box":4,"shots_off_target":1,"final_third_phase":"17/34 (50%)","shots_outside_box":1,"big_chances_missed":1,"big_chances_scored":1,"final_third_entries":25,"fouled_in_final_third":1,"touches_in_penalty_area":7},"home":{"duels":49,"fouls":6,"passes":171,"crosses":"3/11 (27%)","tackles":10,"dribbles":"1/5 (20%)","offsides":2,"red_cards":0,"throw_ins":10,"clearances":8,"free_kicks":7,"goal_kicks":0,"long_balls":"11/23 (48%)","recoveries":24,"big_chances":3,"tackles_won":70,"total_saves":2,"total_shots":5,"aerial_duels":"5/14 (36%)","corner_kicks":4,"dispossessed":3,"ground_duels":"17/31 (55%)","hit_woodwork":0,"yellow_cards":1,"blocked_shots":1,"interceptions":5,"total_tackles":10,"expected_goals":0.65,"accurate_passes":132,"ball_possession":60,"goals_prevented":0.04,"shots_on_target":3,"goalkeeper_saves":2,"shots_inside_box":4,"shots_off_target":2,"final_third_phase":"31/49 (63%)","shots_outside_box":1,"big_chances_missed":2,"big_chances_scored":1,"final_third_entries":32,"fouled_in_final_third":2,"touches_in_penalty_area":11}}}]