[{"id":6551,"api_id":14598736,"league":{"id":22,"api_id":247,"name":"Parva Liga","country":"Bulgaria","season_id":76882,"is_women":false},"home_team":"Lokomotiv Sofia","away_team":"Beroe Stara Zagora","home_team_obj":{"id":341,"api_id":3277,"name":"Lokomotiv Sofia","short_name":"Lokomotiv Sofia","country":"Bulgaria"},"away_team_obj":{"id":353,"api_id":3281,"name":"Beroe Stara Zagora","short_name":"Beroe","country":"Bulgaria"},"event_date":"2026-04-09T16:30:00+04:00","status":"2nd_half","home_score":1,"away_score":1,"home_score_ht":0,"away_score_ht":1,"current_minute":74,"period":"2T","incidents":[{"type":"substitution","minute":68,"is_home":false,"player_in":"J. Sérgio","player_out":"D. V. Juan"},{"type":"substitution","minute":68,"is_home":true,"player_in":"G. Minchev","player_out":"D. Raposo"},{"type":"card","minute":66,"player":"R. Bidounga","is_home":true,"card_type":"yellow","player_id":869935},{"type":"goal","minute":57,"player":"S. Delev","is_home":true,"goal_type":"regular","player_id":80999,"away_score":1,"home_score":1},{"type":"card","minute":45,"player":"D. Yankov","is_home":true,"card_type":"yellow","player_id":928282},{"type":"goal","assist":"J. Pineda","minute":42,"player":"D. V. Juan","is_home":false,"goal_type":"regular","player_id":2456629,"away_score":1,"home_score":0},{"type":"card","minute":22,"player":"A. Lyaskov","is_home":true,"card_type":"yellow","player_id":827395}],"live_stats":null}]