[{"id":9266,"league":{"id":33,"name":"Copa Sudamericana","country":"South America","is_women":false,"current_season":{"id":114,"name":"CONMEBOL Sudamericana 2026","year":2026,"start_date":"2026-01-01","end_date":"2026-12-31"}},"home_team":"São Paulo","away_team":"O'Higgins","home_team_obj":{"id":158,"name":"São Paulo","short_name":"São Paulo","country":"Brazil","coach":{"name":"Roger Machado","shortName":"R. Machado"}},"away_team_obj":{"id":735,"name":"O'Higgins","short_name":"O'Higgins","country":"Chile","coach":{"name":"Lucas Bovaglio","shortName":"L. Bovaglio"}},"event_date":"2026-04-15T02:00:00+04:00","status":"1st_half","home_score":1,"away_score":0,"home_score_ht":null,"away_score_ht":null,"current_minute":41,"period":"1T","incidents":[{"type":"substitution","minute":36,"is_home":true,"player_in":"Danielzinho","player_out":"M. Antônio"},{"type":"card","minute":17,"player":"J. Calleri","is_home":true,"card_type":"yellow","player_id":340519},{"type":"card","minute":15,"player":"F. Ogaz","is_home":false,"card_type":"yellow","player_id":1177211},{"type":"goal","assist":"J. Calleri","minute":8,"player":"Luciano","is_home":true,"sequence":[{"end":{"x":39.6,"y":65.6},"pid":1015261,"pos":{"x":45.8,"y":29.7},"event":"pass","player":"D. Bobadilla"},{"end":{"x":58.6,"y":88.5},"pid":875402,"pos":{"x":39.6,"y":65.6},"event":"ball-movement","player":"A. Franco"},{"end":{"x":58.6,"y":88.5},"pid":875402,"pos":{"x":54.3,"y":69.9},"event":"pass","player":"A. Franco"},{"end":{"x":58.3,"y":72.4},"pid":932937,"pos":{"x":58.3,"y":88.8},"event":"pass","player":"E. Díaz"},{"end":{"x":78.7,"y":60.6},"pid":905453,"pos":{"x":60.5,"y":71.7},"event":"pass","player":"M. Antônio"},{"end":{"x":77.8,"y":53.4},"pid":340519,"pos":{"x":78.7,"y":60.6},"event":"pass","assist":true,"player":"J. Calleri"},{"gk":{"x":98.1,"y":50.7},"gm":{"x":66.13,"y":97.83},"pid":282557,"pos":{"x":77.8,"y":53.4},"body":"left-foot","event":"goal","player":"Luciano"}],"goal_type":"regular","player_id":282557,"away_score":0,"home_score":1}],"live_stats":{"away":{"duels":54,"fouls":3,"passes":181,"crosses":"4/8 (50)","tackles":11,"dribbles":"1/6 (17)","offsides":2,"throw_ins":7,"clearances":9,"free_kicks":2,"goal_kicks":3,"long_balls":"12/21 (57)","recoveries":15,"big_chances":1,"tackles_won":55,"total_saves":0,"total_shots":9,"aerial_duels":"5/9 (56)","corner_kicks":5,"dispossessed":2,"ground_duels":"14/26 (54)","hit_woodwork":0,"yellow_cards":1,"blocked_shots":4,"interceptions":3,"through_balls":1,"total_tackles":11,"expected_goals":"0.48","accurate_passes":152,"ball_possession":49,"goals_prevented":"-0.82","shots_on_target":3,"goalkeeper_saves":0,"shots_inside_box":4,"shots_off_target":2,"final_third_phase":"10/21 (48)","shots_outside_box":5,"big_chances_missed":1,"final_third_entries":16,"touches_in_penalty_area":6},"home":{"duels":46,"fouls":2,"passes":192,"crosses":"1/2 (50)","tackles":7,"dribbles":"2/11 (18)","offsides":0,"throw_ins":13,"clearances":14,"free_kicks":3,"goal_kicks":2,"long_balls":"3/9 (33)","recoveries":15,"big_chances":0,"tackles_won":71,"total_saves":3,"total_shots":2,"aerial_duels":"4/9 (44)","corner_kicks":0,"dispossessed":2,"ground_duels":"12/26 (46)","hit_woodwork":0,"yellow_cards":1,"blocked_shots":0,"interceptions":2,"through_balls":0,"total_tackles":7,"expected_goals":"0.09","accurate_passes":174,"ball_possession":51,"goals_prevented":"0.39","shots_on_target":1,"goalkeeper_saves":3,"shots_inside_box":1,"shots_off_target":1,"final_third_phase":"17/25 (68)","shots_outside_box":1,"big_chances_missed":0,"final_third_entries":16,"touches_in_penalty_area":4}}},{"id":9379,"league":{"id":32,"name":"Copa Libertadores","country":"South America","is_women":false,"current_season":{"id":96,"name":"CONMEBOL Libertadores 2026","year":2026,"start_date":"2026-01-01","end_date":"2026-12-31"}},"home_team":"Nacional","away_team":"Deportes Tolima","home_team_obj":{"id":784,"name":"Nacional","short_name":"Nacional","country":"Uruguay","coach":{"name":"Jorge Bava","shortName":"J. Bava"}},"away_team_obj":{"id":781,"name":"Deportes Tolima","short_name":"Tolima","country":"Colombia","coach":{"name":"Lucas González","shortName":"L. González"}},"event_date":"2026-04-15T02:00:00+04:00","status":"1st_half","home_score":0,"away_score":0,"home_score_ht":null,"away_score_ht":null,"current_minute":43,"period":"1T","incidents":[{"type":"card","minute":41,"player":"D. Pedrozo","is_home":false,"card_type":"yellow","player_id":1174882},{"type":"card","minute":37,"player":"L. Boggio","is_home":true,"card_type":"yellow","player_id":980190},{"type":"card","minute":14,"player":"L. Sandoval","is_home":false,"card_type":"yellow","player_id":848048}],"live_stats":{"away":{"duels":45,"fouls":11,"passes":231,"crosses":"0/2 (0)","tackles":6,"dribbles":"2/8 (25)","offsides":2,"throw_ins":10,"clearances":6,"free_kicks":6,"goal_kicks":5,"long_balls":"5/19 (26)","recoveries":13,"big_chances":0,"tackles_won":50,"total_saves":1,"total_shots":1,"aerial_duels":"6/8 (75)","corner_kicks":1,"dispossessed":1,"ground_duels":"14/36 (39)","hit_woodwork":0,"yellow_cards":2,"blocked_shots":0,"interceptions":2,"total_tackles":6,"expected_goals":"0.01","accurate_passes":199,"ball_possession":56,"goals_prevented":"0.13","shots_on_target":0,"goalkeeper_saves":1,"shots_inside_box":0,"shots_off_target":1,"final_third_phase":"10/16 (63)","shots_outside_box":1,"big_chances_missed":0,"final_third_entries":11,"fouled_in_final_third":0,"touches_in_penalty_area":0},"home":{"duels":55,"fouls":6,"passes":180,"crosses":"2/7 (29)","tackles":7,"dribbles":"4/7 (57)","offsides":0,"throw_ins":5,"clearances":4,"free_kicks":11,"goal_kicks":1,"long_balls":"10/24 (42)","recoveries":23,"big_chances":1,"tackles_won":86,"total_saves":0,"total_shots":3,"aerial_duels":"2/8 (25)","corner_kicks":1,"dispossessed":3,"ground_duels":"22/36 (61)","hit_woodwork":0,"yellow_cards":1,"blocked_shots":0,"interceptions":3,"total_tackles":7,"expected_goals":"0.22","accurate_passes":141,"ball_possession":44,"goals_prevented":"0.00","shots_on_target":1,"goalkeeper_saves":0,"shots_inside_box":1,"shots_off_target":2,"final_third_phase":"28/47 (60)","shots_outside_box":2,"big_chances_missed":1,"final_third_entries":26,"fouled_in_final_third":2,"touches_in_penalty_area":5}}},{"id":9378,"league":{"id":32,"name":"Copa Libertadores","country":"South America","is_women":false,"current_season":{"id":96,"name":"CONMEBOL Libertadores 2026","year":2026,"start_date":"2026-01-01","end_date":"2026-12-31"}},"home_team":"Estudiantes de La Plata","away_team":"Cusco FC","home_team_obj":{"id":787,"name":"Estudiantes de La Plata","short_name":"Estudiantes","country":"Argentina","coach":{"name":"Alexander Medina","shortName":"A. Medina"}},"away_team_obj":{"id":788,"name":"Cusco FC","short_name":"Cusco","country":"Peru","coach":{"name":"Alejandro Orfila","shortName":"A. Orfila"}},"event_date":"2026-04-15T02:00:00+04:00","status":"1st_half","home_score":1,"away_score":1,"home_score_ht":null,"away_score_ht":null,"current_minute":42,"period":"1T","incidents":[{"type":"goal","assist":"D. Soto","minute":31,"player":"L. Colitto","is_home":false,"sequence":[{"end":{"x":47.4,"y":60.2},"pid":586956,"pos":{"x":43.8,"y":70.2},"event":"pass","player":"L. Colitto"},{"end":{"x":41.5,"y":92.7},"pid":973566,"pos":{"x":47.4,"y":60.2},"event":"pass","player":"O. Valenzuela"},{"end":{"x":33.4,"y":96},"pid":1016982,"pos":{"x":39.3,"y":91.7},"event":"pass","player":"M. Ruidías"},{"end":{"x":22.7,"y":82.4},"pid":830742,"pos":{"x":31.9,"y":96.5},"event":"pass","player":"Gabriel Carabajal"},{"end":{"x":13.4,"y":66.9},"pid":980141,"pos":{"x":21.5,"y":82.4},"event":"pass","assist":true,"player":"D. Soto"},{"gk":{"x":1.2,"y":51.8},"gm":{"x":34.41,"y":95.83},"pid":586956,"pos":{"x":9.9,"y":58.5},"body":"right-foot","event":"goal","player":"L. Colitto"}],"goal_type":"regular","player_id":586956,"away_score":1,"home_score":1},{"type":"card","minute":30,"player":"E. Piovi","is_home":true,"card_type":"yellow","player_id":359098},{"type":"goal","minute":28,"player":"F. Farías","is_home":true,"sequence":[{"gk":{"x":88.2,"y":55.8},"gm":{"x":52.15,"y":90.5},"pid":1003907,"pos":{"x":87.5,"y":50},"body":"right-foot","event":"goal","player":"F. Farías"}],"goal_type":"regular","player_id":1003907,"away_score":0,"home_score":1}],"live_stats":{"away":{"duels":49,"fouls":1,"passes":160,"crosses":"1/1 (100)","tackles":12,"dribbles":"1/5 (20)","offsides":2,"big_saves":1,"throw_ins":8,"clearances":12,"free_kicks":4,"goal_kicks":9,"long_balls":"12/22 (55)","recoveries":18,"big_chances":2,"tackles_won":75,"total_saves":2,"total_shots":3,"aerial_duels":"0/5 (0)","corner_kicks":0,"dispossessed":6,"ground_duels":"17/30 (57)","hit_woodwork":0,"yellow_cards":0,"blocked_shots":0,"interceptions":1,"total_tackles":12,"expected_goals":"0.72","accurate_passes":133,"ball_possession":46,"goals_prevented":"0.37","shots_on_target":2,"goalkeeper_saves":2,"shots_inside_box":2,"shots_off_target":1,"final_third_phase":"14/21 (67)","shots_outside_box":1,"big_chances_missed":1,"big_chances_scored":1,"final_third_entries":8,"errors_lead_to_a_goal":1,"errors_lead_to_a_shot":1,"touches_in_penalty_area":5},"home":{"duels":51,"fouls":4,"passes":180,"crosses":"3/12 (25)","tackles":10,"dribbles":"2/8 (25)","offsides":0,"big_saves":1,"throw_ins":10,"clearances":2,"free_kicks":1,"goal_kicks":2,"long_balls":"7/12 (58)","recoveries":20,"big_chances":1,"tackles_won":60,"total_saves":1,"total_shots":11,"aerial_duels":"5/5 (100)","corner_kicks":3,"dispossessed":6,"ground_duels":"13/30 (43)","hit_woodwork":0,"yellow_cards":1,"blocked_shots":3,"interceptions":2,"total_tackles":10,"expected_goals":"0.91","accurate_passes":155,"ball_possession":54,"goals_prevented":"-0.27","shots_on_target":3,"goalkeeper_saves":1,"shots_inside_box":7,"shots_off_target":5,"final_third_phase":"41/57 (72)","shots_outside_box":4,"big_chances_missed":0,"big_chances_scored":1,"final_third_entries":22,"errors_lead_to_a_goal":0,"errors_lead_to_a_shot":1,"touches_in_penalty_area":16}}},{"id":9380,"league":{"id":32,"name":"Copa Libertadores","country":"South America","is_women":false,"current_season":{"id":96,"name":"CONMEBOL Libertadores 2026","year":2026,"start_date":"2026-01-01","end_date":"2026-12-31"}},"home_team":"Cerro Porteño","away_team":"Junior Barranquilla","home_team_obj":{"id":791,"name":"Cerro Porteño","short_name":"Cerro Porteño","country":"Paraguay","coach":{"name":"Ariel Holan","shortName":"A. Holan"}},"away_team_obj":{"id":789,"name":"Junior Barranquilla","short_name":"Junior Barranquilla","country":"Colombia","coach":{"name":"Alfredo Arias","shortName":"A. Arias"}},"event_date":"2026-04-15T02:00:00+04:00","status":"1st_half","home_score":0,"away_score":0,"home_score_ht":null,"away_score_ht":null,"current_minute":43,"period":"1T","incidents":[{"type":"card","minute":38,"player":"G. Benitez","is_home":true,"card_type":"yellow","player_id":830583},{"type":"card","minute":37,"player":"J. D. Ríos","is_home":false,"card_type":"yellow","player_id":829864},{"type":"card","minute":26,"player":"E. R. P. Torales","is_home":true,"card_type":"yellow","player_id":1654426}],"live_stats":{"away":{"duels":47,"fouls":6,"passes":176,"crosses":"1/4 (25)","punches":1,"tackles":6,"dribbles":"0/5 (0)","offsides":1,"throw_ins":14,"clearances":14,"free_kicks":6,"goal_kicks":2,"long_balls":"7/20 (35)","recoveries":19,"big_chances":0,"high_claims":1,"tackles_won":50,"total_saves":2,"total_shots":4,"aerial_duels":"9/18 (50)","corner_kicks":1,"dispossessed":3,"ground_duels":"12/27 (44)","hit_woodwork":0,"yellow_cards":1,"blocked_shots":1,"interceptions":3,"total_tackles":6,"expected_goals":"0.54","accurate_passes":133,"ball_possession":53,"goals_prevented":"0.25","shots_on_target":3,"goalkeeper_saves":2,"shots_inside_box":2,"shots_off_target":0,"final_third_phase":"32/48 (67)","shots_outside_box":2,"big_chances_missed":0,"final_third_entries":25,"fouled_in_final_third":0,"touches_in_penalty_area":3},"home":{"duels":53,"fouls":6,"passes":154,"crosses":"2/9 (22)","punches":0,"tackles":9,"dribbles":"1/4 (25)","offsides":0,"throw_ins":10,"clearances":9,"free_kicks":6,"goal_kicks":3,"long_balls":"14/31 (45)","recoveries":21,"big_chances":1,"high_claims":0,"tackles_won":78,"total_saves":2,"total_shots":3,"aerial_duels":"9/18 (50)","corner_kicks":3,"dispossessed":4,"ground_duels":"16/29 (55)","hit_woodwork":0,"yellow_cards":2,"blocked_shots":1,"interceptions":5,"total_tackles":9,"expected_goals":"0.32","accurate_passes":113,"ball_possession":47,"goals_prevented":"0.32","shots_on_target":2,"goalkeeper_saves":2,"shots_inside_box":1,"shots_off_target":0,"final_third_phase":"31/51 (61)","shots_outside_box":2,"big_chances_missed":1,"final_third_entries":21,"fouled_in_final_third":1,"touches_in_penalty_area":3}}},{"id":9267,"league":{"id":33,"name":"Copa Sudamericana","country":"South America","is_women":false,"current_season":{"id":114,"name":"CONMEBOL Sudamericana 2026","year":2026,"start_date":"2026-01-01","end_date":"2026-12-31"}},"home_team":"Grêmio","away_team":"Deportivo Riestra","home_team_obj":{"id":154,"name":"Grêmio","short_name":"Grêmio","country":"Brazil","coach":{"name":"Luís Castro","shortName":"L. Castro"}},"away_team_obj":{"id":743,"name":"Deportivo Riestra","short_name":"Dep. Riestra","country":"Argentina","coach":{"name":"Guillermo Duro","shortName":"G. Duro"}},"event_date":"2026-04-15T02:00:00+04:00","status":"1st_half","home_score":0,"away_score":0,"home_score_ht":null,"away_score_ht":null,"current_minute":42,"period":"1T","incidents":[],"live_stats":{"away":{"duels":33,"fouls":4,"passes":58,"crosses":"1/2 (50)","tackles":6,"dribbles":"0/4 (0)","offsides":1,"throw_ins":4,"clearances":21,"free_kicks":2,"goal_kicks":4,"long_balls":"4/19 (21)","recoveries":14,"high_claims":1,"tackles_won":100,"total_saves":1,"total_shots":2,"aerial_duels":"2/10 (20)","corner_kicks":1,"dispossessed":1,"ground_duels":"8/20 (40)","hit_woodwork":0,"blocked_shots":0,"interceptions":3,"total_tackles":6,"expected_goals":"0.04","accurate_passes":29,"ball_possession":14,"goals_prevented":"0.01","shots_on_target":0,"goalkeeper_saves":1,"shots_inside_box":0,"shots_off_target":2,"final_third_phase":"12/28 (43)","shots_outside_box":2,"final_third_entries":17,"fouled_in_final_third":0,"touches_in_penalty_area":1},"home":{"duels":66,"fouls":2,"passes":353,"crosses":"0/12 (0)","tackles":4,"dribbles":"4/7 (57)","offsides":0,"throw_ins":7,"clearances":3,"free_kicks":4,"goal_kicks":4,"long_balls":"15/21 (71)","recoveries":11,"high_claims":0,"tackles_won":25,"total_saves":0,"total_shots":5,"aerial_duels":"7/9 (78)","corner_kicks":3,"dispossessed":3,"ground_duels":"12/20 (60)","hit_woodwork":0,"blocked_shots":2,"interceptions":2,"total_tackles":4,"expected_goals":"0.09","accurate_passes":323,"ball_possession":86,"goals_prevented":"0.00","shots_on_target":1,"goalkeeper_saves":0,"shots_inside_box":1,"shots_off_target":2,"final_third_phase":"72/88 (82)","shots_outside_box":4,"final_third_entries":58,"fouled_in_final_third":1,"touches_in_penalty_area":4}}}]