[{"id":3330,"league":{"id":11,"name":"Trendyol Super Lig","country":"Turkey","is_women":false,"current_season":{"id":380,"name":"Super Lig 25/26","year":2025,"start_date":"2025-07-01","end_date":"2026-06-30"}},"home_team":"Gaziantep FK","away_team":"Kayserispor","home_team_obj":{"id":183,"name":"Gaziantep FK","short_name":"Gaziantep","country":"Türkiye","coach":{"name":"Burak Yilmaz","shortName":"B. Yilmaz"},"venue":{"id":179,"name":"Gaziantep Stadium","city":"Gaziantep","country":"Türkiye","capacity":33502}},"away_team_obj":{"id":195,"name":"Kayserispor","short_name":"Kayserispor","country":"Türkiye","coach":{"name":"Erling Moe","shortName":"E. Moe"},"venue":{"id":190,"name":"Kadir Has Stadium","city":"Kayseri","country":"Türkiye","capacity":32864}},"event_date":"2026-04-20T21:00:00+04:00","status":"halftime","home_score":2,"away_score":0,"home_score_ht":1,"away_score_ht":1,"penalty_shootout":null,"current_minute":45,"period":"HT","incidents":[{"type":"goal","minute":45,"player":"Y. A. Bennasser","is_home":true,"sequence":[{"end":{"x":61.2,"y":22.3},"pid":958167,"pos":{"x":43.2,"y":36},"event":"pass","player":"D. Camara"},{"end":{"x":71.9,"y":31.8},"pid":984602,"pos":{"x":61.2,"y":22.3},"event":"ball-movement","player":"K. Kozłowski"},{"end":{"x":71.9,"y":31.8},"pid":984602,"pos":{"x":82.1,"y":15.7},"event":"pass","player":"K. Kozłowski"},{"gk":{"x":98.6,"y":48.4},"gm":{"x":40.7,"y":95.33},"pid":958167,"pos":{"x":72.8,"y":34.6},"event":"miss","player":"D. Camara"},{"gk":{"x":3.5,"y":50.7},"gm":{"x":74.19,"y":93.67},"pid":802850,"pos":{"x":74.4,"y":32.8},"body":"left-foot","event":"goal","player":"Y. A. Bennasser"}],"goal_type":"ownGoal","player_id":802850,"away_score":0,"home_score":2},{"type":"card","minute":42,"player":"L. Benes","is_home":false,"card_type":"yellow","player_id":354558},{"type":"substitution","minute":34,"is_home":false,"player_in":"R. Civelek","player_out":"J. Brenet","player_in_id":781408,"player_out_id":296438},{"type":"goal","assist":"K. Kozłowski","minute":25,"player":"M. Bayo","is_home":true,"sequence":[{"end":{"x":99,"y":28.5},"pid":797602,"pos":{"x":66.2,"y":0},"event":"throw-in","player":"D. Sorescu"},{"end":{"x":90.7,"y":42.5},"pid":984602,"pos":{"x":97.9,"y":31.8},"event":"pass","assist":true,"player":"K. Kozłowski"},{"gk":{"x":98.6,"y":47.8},"gm":{"x":25.27,"y":55.67},"pid":909318,"pos":{"x":90.7,"y":42.5},"body":"right-foot","event":"goal","player":"M. Bayo"}],"goal_type":"regular","player_id":909318,"away_score":0,"home_score":1},{"type":"card","minute":17,"player":"V. N. Gidado","is_home":true,"card_type":"yellow","player_id":1632791}],"live_stats":{"away":{"duels":42,"fouls":4,"passes":193,"crosses":"2/9 (22)","punches":1,"tackles":5,"dribbles":"5/7 (71)","offsides":1,"big_saves":1,"throw_ins":7,"clearances":10,"free_kicks":6,"goal_kicks":5,"long_balls":"10/22 (45)","recoveries":20,"big_chances":1,"tackles_won":60,"total_saves":1,"total_shots":3,"aerial_duels":"1/8 (13)","corner_kicks":0,"dispossessed":4,"ground_duels":"15/30 (50)","hit_woodwork":0,"yellow_cards":1,"blocked_shots":0,"interceptions":6,"through_balls":1,"total_tackles":5,"expected_goals":"0.33","accurate_passes":164,"ball_possession":42,"goals_prevented":"-1.13","shots_on_target":2,"goalkeeper_saves":1,"shots_inside_box":3,"shots_off_target":1,"final_third_phase":"27/43 (63)","shots_outside_box":0,"big_chances_missed":1,"big_chances_scored":0,"final_third_entries":31,"errors_lead_to_a_goal":1,"fouled_in_final_third":1,"touches_in_penalty_area":8},"home":{"duels":58,"fouls":6,"passes":261,"crosses":"4/9 (44)","punches":0,"tackles":6,"dribbles":"5/9 (56)","offsides":0,"big_saves":0,"throw_ins":9,"clearances":6,"free_kicks":4,"goal_kicks":2,"long_balls":"15/22 (68)","recoveries":22,"big_chances":1,"tackles_won":50,"total_saves":2,"total_shots":10,"aerial_duels":"7/8 (88)","corner_kicks":3,"dispossessed":1,"ground_duels":"15/30 (50)","hit_woodwork":1,"yellow_cards":1,"blocked_shots":4,"interceptions":6,"through_balls":0,"total_tackles":6,"expected_goals":"0.53","accurate_passes":230,"ball_possession":58,"goals_prevented":"0.60","shots_on_target":2,"goalkeeper_saves":2,"shots_inside_box":5,"shots_off_target":4,"final_third_phase":"39/59 (66)","shots_outside_box":5,"big_chances_missed":0,"big_chances_scored":1,"final_third_entries":32,"errors_lead_to_a_goal":0,"fouled_in_final_third":1,"touches_in_penalty_area":21}}},{"id":7992,"league":{"id":25,"name":"Ekstraklasa","country":"Poland","is_women":false,"current_season":{"id":271,"name":"Ekstraklasa 25/26","year":2025,"start_date":"2025-07-01","end_date":"2026-06-30"}},"home_team":"KS Lechia Gdańsk","away_team":"Piast Gliwice","home_team_obj":{"id":430,"name":"KS Lechia Gdańsk","short_name":"Lechia","country":"Poland","coach":{"name":"John Carver","shortName":"J. Carver"},"venue":{"id":411,"name":"Polsat Plus Arena Gdańsk","city":"Gdansk","country":"Poland","capacity":41620}},"away_team_obj":{"id":435,"name":"Piast Gliwice","short_name":"Piast","country":"Poland","coach":{"name":"Daniel Myśliwiec","shortName":"Daniel Myśliwiec"},"venue":{"id":415,"name":"Stadion Miejski w Gliwicach","city":"Gliwice","country":"Poland","capacity":10037}},"event_date":"2026-04-20T21:00:00+04:00","status":"halftime","home_score":0,"away_score":0,"home_score_ht":0,"away_score_ht":0,"penalty_shootout":null,"current_minute":45,"period":"HT","incidents":[{"type":"card","minute":31,"player":"I. Drapiński","is_home":false,"card_type":"yellow","player_id":1161838},{"type":"substitution","minute":28,"is_home":false,"player_in":"F. Borowski","player_out":"O. Lesniak","player_in_id":1021809,"player_out_id":1388230},{"type":"card","minute":24,"player":"E. Twumasi","is_home":false,"card_type":"red","player_id":931738}],"live_stats":{"away":{"duels":45,"fouls":2,"passes":195,"crosses":"1/5 (20)","tackles":5,"dribbles":"3/11 (27)","offsides":0,"red_cards":1,"throw_ins":7,"clearances":24,"free_kicks":6,"goal_kicks":4,"long_balls":"11/28 (39)","recoveries":31,"tackles_won":80,"total_saves":3,"total_shots":4,"aerial_duels":"9/21 (43)","corner_kicks":0,"dispossessed":2,"ground_duels":"14/30 (47)","hit_woodwork":0,"yellow_cards":1,"blocked_shots":2,"interceptions":4,"total_tackles":5,"expected_goals":"0.35","accurate_passes":158,"ball_possession":49,"goals_prevented":"0.22","shots_on_target":0,"goalkeeper_saves":3,"shots_inside_box":2,"shots_off_target":2,"final_third_phase":"42/53 (79)","shots_outside_box":2,"final_third_entries":25,"touches_in_penalty_area":4},"home":{"duels":55,"fouls":6,"passes":193,"crosses":"5/18 (28)","tackles":10,"dribbles":"4/7 (57)","offsides":1,"red_cards":0,"throw_ins":21,"clearances":4,"free_kicks":2,"goal_kicks":2,"long_balls":"9/28 (32)","recoveries":27,"tackles_won":70,"total_saves":0,"total_shots":9,"aerial_duels":"12/21 (57)","corner_kicks":6,"dispossessed":2,"ground_duels":"16/30 (53)","hit_woodwork":0,"yellow_cards":0,"blocked_shots":4,"interceptions":4,"total_tackles":10,"expected_goals":"0.67","accurate_passes":152,"ball_possession":51,"goals_prevented":"0.00","shots_on_target":3,"goalkeeper_saves":0,"shots_inside_box":6,"shots_off_target":2,"final_third_phase":"58/84 (69)","shots_outside_box":3,"final_third_entries":38,"touches_in_penalty_area":17}}},{"id":7671,"league":{"id":23,"name":"Superliga","country":"Romania","is_women":false,"current_season":{"id":374,"name":"Superliga 25/26","year":2025,"start_date":"2025-07-01","end_date":"2026-06-30"}},"home_team":"FC Farul Constanța","away_team":"FCSB","home_team_obj":{"id":366,"name":"FC Farul Constanța","short_name":"Farul Constanța","country":"Romania","coach":{"name":"Flavius Stoican","shortName":"F. Stoican"},"venue":{"id":346,"name":"Stadionul Central-Academia Gheorghe Hagi","city":"Ovidiu","country":"Romania","capacity":4554}},"away_team_obj":{"id":140,"name":"FCSB","short_name":"FCSB","country":"Romania","coach":{"name":"Mirel Radoi","shortName":"M. Radoi"},"venue":{"id":138,"name":"National Arena","city":"Bucharest","country":"Romania","capacity":55634}},"event_date":"2026-04-20T21:30:00+04:00","status":"1st_half","home_score":0,"away_score":0,"home_score_ht":null,"away_score_ht":null,"penalty_shootout":null,"current_minute":24,"period":"1T","incidents":[{"type":"substitution","minute":22,"is_home":false,"player_in":"G. O. Popescu","player_out":"D. Miculescu","player_in_id":1067660,"player_out_id":905096}],"live_stats":{"away":{"duels":58,"fouls":3,"passes":130,"crosses":"0/2 (0)","punches":0,"tackles":1,"dribbles":"1/2 (50)","offsides":0,"throw_ins":4,"clearances":7,"free_kicks":2,"goal_kicks":2,"long_balls":"6/13 (46)","recoveries":14,"tackles_won":0,"total_saves":0,"total_shots":3,"aerial_duels":"3/4 (75)","corner_kicks":1,"dispossessed":1,"ground_duels":"4/8 (50)","hit_woodwork":0,"blocked_shots":0,"interceptions":5,"through_balls":1,"total_tackles":1,"accurate_passes":107,"ball_possession":56,"shots_on_target":1,"goalkeeper_saves":0,"shots_inside_box":2,"shots_off_target":2,"final_third_phase":"17/24 (71)","shots_outside_box":1,"final_third_entries":13,"touches_in_penalty_area":3},"home":{"duels":42,"fouls":2,"passes":98,"crosses":"1/5 (20)","punches":1,"tackles":2,"dribbles":"0/1 (0)","offsides":1,"throw_ins":5,"clearances":2,"free_kicks":3,"goal_kicks":7,"long_balls":"3/15 (20)","recoveries":11,"tackles_won":100,"total_saves":1,"total_shots":0,"aerial_duels":"1/4 (25)","corner_kicks":1,"dispossessed":0,"ground_duels":"4/8 (50)","hit_woodwork":0,"blocked_shots":0,"interceptions":4,"through_balls":0,"total_tackles":2,"accurate_passes":71,"ball_possession":44,"shots_on_target":0,"goalkeeper_saves":1,"shots_inside_box":0,"shots_off_target":0,"final_third_phase":"21/35 (60)","shots_outside_box":0,"final_third_entries":20,"touches_in_penalty_area":1}}}]